xi_pipes/__init__.py
xi_pipes-0.0.8.dist-info/METADATA
xi_pipes-0.0.8.dist-info/WHEEL
xi_pipes-0.0.8.dist-info/top_level.txt
xi_pipes-0.0.8.dist-info/RECORD
