Metadata-Version: 2.2
Name: xi-pipes
Version: 0.0.8
Summary: Custom pipes
Author-email: Javier Iserte <javiserte@gmail.com>
Requires-Dist: pipe
